{
  "waveIndex": 1,
  "isMultiMap": false,
  "wallHeight": 12,
  "maps": [
    {
      "file": "1_8",
      "duration": 60
    }
  ],
  "isRandomPos": true,
  "enemies": [
    {
      "type": 101,
      "count": 6,
      "spawnDelay": 15
    },
    {
      "type": 111,
      "count": 6,
      "spawnDelay": 15
    },
    {
      "type": 102,
      "count": 6,
      "spawnDelay": 30
    }
  ],
  "mission": {
    "type": "Item",
    "count": 4,
    "itemPoints": [
      {
        "x": 4,
        "y": 25
      },
      {
        "x": 4,
        "y": 4
      },
      {
        "x": 25,
        "y": 4
      },
      {
        "x": 25,
        "y": 25
      }
    ]


  },

  "isRandomEvent": false,
  "events": [

  ]
}
